<?xml version='1.0' encoding='UTF-8'?>
<song xmlns="http://openlyrics.info/namespace/2009/song" version="0.8" createdIn="OpenLP 2.9.4" modifiedIn="OpenLP 2.9.4" modifiedDate="2022-06-13T16:16:50">
  <properties>
    <titles>
      <title>Albowiem tak Bóg świat umiłował</title>
    </titles>
    <verseOrder>v1</verseOrder>
    <authors>
      <author>Autor nieznany</author>
    </authors>
  </properties>
  <lyrics>
    <verse name="v1">
      <lines>/Albowiem tak Bóg świat umiłował<br/>Że Syna Swego jednorodzonego dał<br/>Ażeby każdy kto w Niego wierzy<br/>Nie zginął ale życie wieczne miał.<br/><br/>O, Jezu, Jezu, Jezu! /x2 //x3</lines>
    </verse>
  </lyrics>
</song>
