<?xml version='1.0' encoding='UTF-8'?>
<song xmlns="http://openlyrics.info/namespace/2009/song" version="0.8" createdIn="OpenLP 2.9.4" modifiedIn="OpenLP 2.9.4" modifiedDate="2022-06-13T16:17:05">
  <properties>
    <titles>
      <title>W sercu mym</title>
    </titles>
    <verseOrder>v1</verseOrder>
    <authors>
      <author>Autor nieznany</author>
    </authors>
  </properties>
  <lyrics>
    <verse name="v1">
      <lines>W sercu mym,<br/>Boże rządź w sercu mym<br/>Jako Król<br/>W sercu mym zawsze rządź<br/>Niech królestwo Twe<br/>We mnie ziści się<br/>Twą wolę pełnić chcę<br/>W sercu moim rządź</lines>
    </verse>
  </lyrics>
</song>
