<?xml version='1.0' encoding='UTF-8'?>
<song xmlns="http://openlyrics.info/namespace/2009/song" version="0.8" createdIn="OpenLP 2.9.4" modifiedIn="OpenLP 2.9.4" modifiedDate="2022-06-13T16:17:06">
  <properties>
    <titles>
      <title>Wzywam tedy bracia was</title>
    </titles>
    <verseOrder>v1 v2</verseOrder>
    <authors>
      <author>Autor nieznany</author>
    </authors>
    <songbooks>
      <songbook name="Śpiewnik Wędrowiec" entry="207"/>
    </songbooks>
  </properties>
  <lyrics>
    <verse name="v1">
      <lines>Wzywam tedy bracia was<br/>Miłosierdziem Bożym:<br/>Złóżcie ciała swoje na ofiarę<br/>Żywą, świętą, miłą Bogu,<br/>Bo taka winna być,<br/>Wasza służba na tej ziemi.</lines>
    </verse>
    <verse name="v2">
      <lines>Wzywam tedy siostry was<br/>Miłosierdziem Bożym:<br/>Złóżcie ciała swoje na ofiarę<br/>Żywą, świętą, miłą Bogu,<br/>Bo taka winna być,<br/>Wasza służba na tej ziemi.</lines>
    </verse>
  </lyrics>
</song>
